{
    "stocks": [
        {
            "MLM": "708.11",
            "AEM": "252.19",
            "WPM": "165.72",
            "FNV": "280.82",
            "AU": "128.26",
            "KGC": "38.07",
            "AGI": "55.33",
            "OR": "47.73",
            "TFPM": "41.36",
            "IAG": "24.57",
            "CIFR": "24.695",
            "OPEN": "10.52",
            "CDE": "27.15",
            "AMRZ": "65.86",
            "ASML": "1526.51",
            "EGO": "49.71",
            "BVN": "43.67",
            "HBM": "28.33",
            "GOOGL": "343.69",
            "FOX": "67.76",
            "TKO": "224.96",
            "SATS": "131.09",
            "DDS": "730.73",
            "AN": "227.18",
            "SGHC": "14.09",
            "ATAT": "42.9",
            "SGI": "97.99",
            "PFGC": "108.72",
            "BMO": "148.85",
            "IX": "36.6",
            "PSLV": "36.35",
            "PFSI": "159.46",
            "NVS": "168.62",
            "HCA": "545.13",
            "ARGX": "929.61",
            "THC": "244.8",
            "MEDP": "620.59",
            "PODD": "352.82",
            "EHC": "127.18",
            "ASND": "242.09",
            "ENSG": "215.83",
            "HALO": "81.23",
            "VRNA": "106.31",
            "ABVX": "138.72",
            "URI": "1020.0",
            "FERG": "267.36",
            "PNR": "112.59",
            "NVT": "122.58",
            "ACM": "134.35",
            "CNM": "66.98",
            "MLI": "139.18",
            "AWI": "203.71",
            "ROAD": "138.88",
            "BE": "174.77",
            "MIR": "29.75",
            "REZI": "44.5",
            "KRMN": "115.29",
            "JLL": "358.66",
            "AVGO": "412.97",
            "ANET": "162.03",
            "GLW": "160.43",
            "STX": "446.57",
            "FLEX": "72.08",
            "CYBR": "522.02",
            "GWRE": "261.88",
            "FN": "615.99",
            "UI": "809.36",
            "NXT": "124.49",
            "CLS": "352.61",
            "CRDO": "189.19",
            "TSEM": "172.13",
            "LITE": "783.25",
            "LIF": "110.89",
            "SNDK": "772.09",
            "SBS": "30.51",
            "VMC": "330.37",
            "GFI": "61.51",
            "NEU": "873.09",
            "HL": "31.81",
            "NTES": "159.34",
            "TTWO": "262.29",
            "LYV": "174.06",
            "APP": "733.6",
            "ORLY": "107.82",
            "AZO": "4354.54",
            "EXPE": "301.31",
            "IBP": "344.19",
            "DORM": "166.34",
            "ATGE": "154.45",
            "HSBC": "94.5",
            "NMR": "9.54",
            "HOOD": "152.46",
            "BAP": "375.25",
            "ACT": "44.19",
            "BSX": "108.14",
            "MDGL": "602.83",
            "INSM": "211.41",
            "ALLE": "179.77",
            "ESLT": "1014.33",
            "FSV": "208.43",
            "TSM": "387.73",
            "NET": "253.3",
            "CIEN": "412.58",
            "ALAB": "251.88",
            "IDCC": "396.54",
            "ESE": "285.79",
            "NBIS": "135.46",
            "CASY": "691.78",
            "FTI": "68.0",
            "MS": "191.23",
            "GS": "975.86",
            "C": "123.77",
            "SAN": "13.21",
            "IREN": "76.41",
            "ALNY": "491.22",
            "MRUS": "94.15",
            "AHR": "53.19",
            "APH": "166.25",
            "RDDT": "270.71",
            "MOD": "238.5",
            "ENB": "54.54",
            "MFG": "10.09",
            "CG": "69.35",
            "HLI": "209.19",
            "EVR": "383.12",
            "ROIV": "29.72",
            "GE": "345.74",
            "FIX": "1468.58",
            "ITT": "208.86",
            "MTZ": "312.72",
            "IESC": "519.67",
            "ORCL": "328.37",
            "TEL": "249.0",
            "HPE": "26.25",
            "PSTG": "98.7",
            "FFIV": "343.17",
            "TTMI": "113.0",
            "TLN": "445.84",
            "CRH": "131.38",
            "RGLD": "304.29",
            "VIK": "79.71",
            "GPI": "488.25",
            "LOPE": "220.55",
            "GHC": "1193.76",
            "JPM": "334.61",
            "BAC": "57.25",
            "UBS": "49.25",
            "BN": "72.73",
            "ING": "30.91",
            "TRV": "312.03",
            "BCS": "27.52",
            "CM": "103.75",
            "L": "112.19",
            "MTG": "29.86",
            "AMG": "330.75",
            "PJT": "191.42",
            "THG": "186.22",
            "BNT": "72.83",
            "ABCB": "85.94",
            "ABBV": "244.38",
            "LH": "290.93",
            "GD": "368.69",
            "PH": "1023.02",
            "LHX": "378.48",
            "CMI": "605.63",
            "RBA": "119.14",
            "CHRW": "200.59",
            "PAC": "300.41",
            "STN": "113.7",
            "AYI": "376.69",
            "R": "224.06",
            "VMI": "477.85",
            "GATX": "198.52",
            "BCO": "135.58",
            "STRL": "459.72",
            "PRIM": "169.36",
            "CBRE": "171.61",
            "LRCX": "249.48",
            "KLAC": "1684.71",
            "SONY": "30.26",
            "TDY": "688.59",
            "RMBS": "125.93",
            "NVMI": "497.63",
            "BDC": "150.91",
            "MNST": "86.66",
            "BK": "127.61",
            "DB": "40.33",
            "SOFI": "32.235",
            "KTOS": "130.72",
            "MU": "461.73",
            "IONQ": "82.09",
            "TJX": "161.73",
            "CCJ": "134.09",
            "SOBO": "33.95",
            "NU": "18.76",
            "PIPR": "378.06",
            "CW": "726.48",
            "UBER": "100.1",
            "APLD": "41.35",
            "OKLO": "174.14",
            "TCOM": "78.96",
            "SU": "63.71",
            "RY": "175.46",
            "WF": "84.47",
            "CAT": "775.0",
            "AXP": "384.89",
            "GLXY": "42.86",
            "QBTS": "44.78",
            "RUSHB": "59.84",
            "COF": "257.94",
            "RJF": "176.43",
            "GL": "146.95",
            "BPOP": "147.56",
            "ESNT": "66.82",
            "RDN": "37.23",
            "NTRA": "254.4",
            "FTAI": "310.04",
            "WTS": "336.18",
            "AEIS": "340.42",
            "CTRE": "41.14",
            "CVLT": "195.41",
            "B": "52.98",
            "CVNA": "478.45",
            "TPR": "160.49",
            "AMAT": "394.95",
            "WFC": "96.39",
            "BBVA": "26.11",
            "UTHR": "544.71",
            "CDNS": "373.37",
            "WDC": "316.93",
            "NXE": "13.92",
            "MUFG": "19.73",
            "DGX": "211.91",
            "MTSR": "53.58",
            "HWM": "265.11",
            "EME": "812.79",
            "AVAV": "409.83",
            "DY": "429.73",
            "NVDA": "206.96",
            "JBL": "277.57",
            "VST": "217.92",
            "HMY": "26.04",
            "GIL": "72.58",
            "NFG": "96.3",
            "AEG": "8.05",
            "MCK": "995.69",
            "WELL": "215.48",
            "WEC": "117.9",
            "WTW": "349.93",
            "ORI": "46.45",
            "COR": "374.75",
            "RTX": "212.16",
            "XEL": "83.91",
            "IDA": "144.43",
            "MP": "98.65",
            "WMB": "76.26",
            "FCFS": "197.09",
            "SNX": "172.2",
            "EA": "204.79",
            "WRB": "78.46",
            "ATO": "188.58",
            "EVRG": "84.41",
            "RBLX": "141.56",
            "BYD": "89.56",
            "DASH": "281.74",
            "BLK": "1202.59",
            "IBKR": "78.42",
            "STT": "136.29",
            "NTRS": "154.8",
            "NSC": "317.83",
            "GRMN": "259.77",
            "ROL": "65.6",
            "ALL": "215.19",
            "BTSG": "43.99",
            "NOC": "768.02",
            "XYL": "152.95",
            "BWXT": "217.89",
            "LNT": "73.03",
            "AEE": "113.33",
            "NEM": "131.95",
            "MT": "67.12",
            "PAAS": "68.7",
            "DTM": "142.41",
            "JNJ": "248.56",
            "VRT": "270.06",
            "RL": "385.03",
            "CINF": "172.65",
            "DCI": "110.57",
            "SYM": "87.3",
            "PANW": "221.38",
            "PLTR": "207.3",
            "ASTS": "122.09",
            "PONY": "24.06",
            "CEG": "403.95",
            "FWONA": "99.33",
            "GSAT": "73.68",
            "FTDR": "69.38",
            "TEM": "103.25",
            "AER": "154.83",
            "NI": "47.56",
            "SCCO": "218.85",
            "SHEL": "92.75",
            "PWR": "577.95",
            "ULS": "91.21",
            "MPWR": "1231.95",
            "SANM": "182.54",
            "AEP": "134.15",
            "DTE": "150.13",
            "CNP": "44.14",
            "K": "83.13",
            "AMD": "264.33",
            "SO": "99.72",
            "SHG": "71.72",
            "CADE": "46.46",
            "J": "164.44",
            "COHR": "298.91",
            "WOLF": "35.42",
            "PTGX": "101.68",
            "CORZ": "22.9",
            "DUK": "133.46",
            "TAC": "17.73",
            "WMT": "133.89",
            "RYTM": "117.62",
            "OGE": "49.25",
            "SSRM": "33.26",
            "ROST": "214.83",
            "SMR": "53.43",
            "SR": "92.76",
            "CIB": "84.53",
            "ASX": "25.11",
            "GILD": "155.8",
            "FTS": "58.56",
            "AAPL": "286.19",
            "GM": "86.38",
            "BOOT": "207.98",
            "ERJ": "66.93",
            "CRS": "412.13",
            "CIGI": "169.29",
            "CRWD": "557.53",
            "CACI": "662.19",
            "PI": "241.91",
            "SF": "133.22",
            "JCI": "145.46",
            "HII": "453.73",
            "RBC": "584.89",
            "IBM": "314.98",
            "SHOP": "179.01",
            "STLD": "205.78",
            "TIMB": "27.5",
            "LYG": "6.25",
            "MFC": "38.55",
            "NWG": "19.07",
            "RNA": "72.93",
            "ROK": "430.31",
            "WWD": "402.56",
            "CX": "13.17",
            "AMX": "26.02",
            "ATI": "166.42",
            "MSFT": "542.25",
            "NOK": "8.65",
            "CSCO": "86.78",
            "FUTU": "199.04",
            "HUBB": "527.9",
            "WCC": "315.27",
            "FLS": "92.04",
            "TER": "342.82",
            "MTSI": "258.54",
            "NRG": "184.03",
            "CAH": "229.88",
            "AME": "241.46",
            "AMZN": "253.905",
            "APG": "45.29",
            "SPXC": "243.04",
            "TS": "57.11",
            "BCH": "46.36",
            "IDXX": "766.68",
            "DD": "51.53",
            "EXPD": "165.04",
            "NBIX": "155.63",
            "PTCT": "86.25",
            "ELP": "10.94",
            "STE": "268.65",
            "RVMD": "123.27",
            "AXSM": "189.1",
            "ECG": "130.1",
            "SITM": "440.8",
            "BKH": "75.76",
            "NYT": "82.69",
            "MKL": "2191.9",
            "LLY": "1109.94",
            "DDOG": "199.72",
            "COKE": "216.91",
            "EQT": "65.23",
            "AZN": "209.48",
            "AMGN": "388.16",
            "GSK": "61.18",
            "ENS": "189.93",
            "KB": "118.21",
            "AGX": "479.9",
            "VTR": "88.0",
            "ENLT": "78.36",
            "SMFG": "23.81",
            "VLO": "242.07",
            "LGN": "58.05",
            "OHI": "48.4",
            "HIG": "143.53",
            "MCY": "96.19",
            "KRYS": "291.93",
            "BLLN": "130.18",
            "HLT": "325.13",
            "H": "171.84",
            "UHS": "244.18",
            "SOLV": "86.14",
            "RYAAY": "73.82",
            "MOG-A": "349.6",
            "CMC": "83.21",
            "MAR": "359.94",
            "GOLF": "103.29",
            "SYF": "88.47",
            "WTM": "2244.14",
            "ADI": "360.8",
            "OGS": "87.7",
            "MPLX": "59.14",
            "OMF": "71.37",
            "IHG": "148.23",
            "EXE": "122.89",
            "BBIO": "79.91",
            "APGE": "82.43",
            "TD": "98.78",
            "LTM": "68.46",
            "KEYS": "313.27",
            "ULTA": "706.82",
            "WAB": "264.78",
            "KYMR": "95.03",
            "AMKR": "56.17",
            "CFG": "68.12",
            "EWBC": "122.56",
            "WTFC": "161.35",
            "FNB": "18.92",
            "DAL": "75.35",
            "GEV": "882.64",
            "SOLS": "80.92",
            "URBN": "82.7",
            "CB": "342.76",
            "RF": "30.95",
            "BOKF": "136.57",
            "ACA": "128.17",
            "PL": "33.83",
            "GVA": "136.19",
            "MSGS": "341.76",
            "AIZ": "243.31",
            "ENIC": "4.5",
            "FER": "74.38",
            "TSLA": "489.82",
            "AXS": "109.18",
            "UAL": "117.53",
            "RRR": "66.79",
            "NNI": "141.13",
            "SCHW": "107.21",
            "NDAQ": "100.98",
            "UL": "74.59",
            "EXEL": "46.61",
            "HEI": "358.04",
            "LAUR": "35.97",
            "BNS": "77.78",
            "FIGR": "73.91",
            "FCX": "68.82",
            "DOO": "73.12",
            "MCO": "539.61",
            "HBAN": "19.27",
            "STEP": "76.27",
            "OSK": "177.94",
            "AXIA-PC": "9.1",
            "AXIA-P": "10.06",
            "JXN": "122.21",
            "HCC": "102.44",
            "SN": "131.45",
            "CVCO": "697.76",
            "AX": "101.01",
            "IFS": "51.5",
            "GMED": "96.71",
            "CR": "210.23",
            "QXO": "27.07",
            "FORM": "105.83",
            "MMS": "98.93",
            "AMTM": "37.53",
            "MRCY": "103.02",
            "CAMT": "172.29",
            "XOM": "161.13",
            "GPCR": "93.79",
            "BLD": "550.9",
            "AL": "64.7",
            "TDS": "47.59",
            "OPCH": "36.59",
            "CMPO": "26.0",
            "ESI": "36.71",
            "AUGO": "89.74",
            "NXST": "253.64",
            "AMCR": "44.16",
            "ALV": "129.58",
            "USFD": "101.98",
            "SNEX": "130.96",
            "PEN": "359.4",
            "LECO": "298.88",
            "CLH": "297.15",
            "AIT": "291.74",
            "NPO": "278.0",
            "MKSI": "262.94",
            "RAL": "56.28",
            "MICC": "19.87",
            "DOV": "233.31",
            "CAE": "34.05",
            "VSEC": "227.78",
            "POWL": "592.9",
            "AG": "32.01",
            "AD": "60.28",
            "RUSHA": "75.26",
            "FITB": "55.08",
            "FHN": "26.23",
            "CBC": "25.19",
            "SNA": "389.59",
            "TKR": "109.99",
            "OMAB": "134.98",
            "Q": "126.76",
            "KOF": "114.27",
            "BSAC": "37.46",
            "MDLN": "49.99",
            "EMR": "161.69",
            "KEX": "133.83",
            "VICR": "209.19",
            "SARO": "33.12",
            "NGG": "93.93",
            "MIRM": "108.62",
            "TECK": "61.43",
            "AKO-B": "33.33",
            "E": "54.73",
            "TGS": "33.5",
            "ORA": "129.71",
            "SBSW": "21.12",
            "AVT": "67.34",
            "RIO": "100.78",
            "TRP": "65.09",
            "VIST": "72.96",
            "MRSH": "189.75",
            "LMT": "676.7",
            "FDX": "388.48",
            "VIAV": "35.35",
            "PLXS": "208.36",
            "KO": "81.56",
            "CME": "326.46",
            "PNC": "242.48",
            "MTB": "238.01",
            "PFG": "97.5",
            "ONB": "25.88",
            "UMBF": "134.32",
            "DE": "662.49",
            "CSX": "43.17",
            "PCAR": "129.48",
            "XPO": "215.37",
            "CPA": "154.09",
            "TXN": "226.56",
            "BHP": "83.01",
            "EPD": "38.11",
            "WBS": "73.83",
            "ITW": "299.6",
            "JBHT": "234.92",
            "ASR": "381.16",
            "LFUS": "376.69",
            "ECL": "308.35",
            "RS": "360.37",
            "MCD": "341.06",
            "ATMU": "65.57",
            "TTE": "90.06",
            "RNR": "310.9",
            "NDSN": "299.29",
            "TIGO": "75.15",
            "AROC": "37.04",
            "AFL": "117.47",
            "RRX": "224.08",
            "YUM": "168.16",
            "WSM": "220.67",
            "BWA": "66.55",
            "BGSI": "182.26",
            "FRO": "39.62",
            "IONS": "86.5",
            "HXL": "94.73",
            "GTES": "28.05",
            "ARW": "159.66",
            "CENX": "58.07",
            "KT": "24.54",
            "TRGP": "244.04",
            "LOW": "287.39",
            "HON": "248.04",
            "PM": "189.8",
            "KMI": "33.96",
            "PBA": "44.99",
            "ETN": "396.09",
            "TT": "472.54",
            "TXT": "100.77",
            "TEX": "69.51",
            "LSCC": "105.77",
            "SYY": "91.16",
            "SLF": "68.95",
            "MSA": "203.08",
            "SBRA": "20.91",
            "GGG": "94.82",
            "NEE": "95.68",
            "SRE": "96.27",
            "ED": "115.46",
            "CMS": "78.29",
            "CCEP": "110.43",
            "CNQ": "50.55",
            "MATX": "171.24",
            "CRUS": "145.98",
            "LIN": "509.34",
            "AS": "41.96",
            "FPS": "36.0",
            "CTVA": "80.52",
            "ALSN": "126.94",
            "OSIS": "297.87",
            "VCTR": "77.27",
            "JAZZ": "196.83",
            "SMTC": "96.3",
            "TNL": "77.19",
            "JBS": "16.89",
            "BRX": "30.64",
            "CNX": "42.61",
            "ADC": "81.92",
            "EMA": "53.68",
            "CVX": "205.21",
            "AM": "23.14",
            "CRC": "64.74",
            "WM": "246.51",
            "LAMR": "139.18",
            "EPRT": "34.59",
            "AAOI": "127.01",
            "CGON": "68.64",
            "MPC": "236.24",
            "KNX": "63.5",
            "INGM": "26.36",
            "SUN": "65.0",
            "LNG": "287.2",
            "PBR": "19.78",
            "BP": "45.86",
            "MDU": "21.34",
            "CF": "136.0",
            "EOG": "139.68",
            "PSX": "178.34",
            "CVE": "25.06",
            "EC": "14.73",
            "KR": "75.6",
            "BG": "125.96",
            "EQNR": "41.6",
            "CTRA": "33.97",
            "EXC": "50.29",
            "VZ": "51.38",
            "MGY": "30.92",
            "FE": "51.76",
            "SEI": "68.56",
            "EQIX": "984.46",
            "PNW": "103.08",
            "WDS": "22.63",
            "LBRT": "31.73",
            "TERN": "49.61",
            "COP": "127.19",
            "RRC": "45.28",
            "PR": "20.07",
            "GLNG": "52.8",
            "KGS": "58.5",
            "PAYP": "24.11"
        }
    ],
    "others": [
        {}
    ]
}