{
    "MLM": "631.12",
    "AEM": "154.18",
    "WPM": "107.37",
    "FNV": "201.85",
    "AU": "66.31",
    "KGC": "23.28",
    "AGI": "33.12",
    "OR": "35.95",
    "TFPM": "28.87",
    "IAG": "11.16",
    "CDE": "15.53",
    "AMRZ": "55.63",
    "EGO": "28.06",
    "BVN": "20.18",
    "HBM": "13.57",
    "GOOGL": "240.8",
    "FOX": "56.81",
    "TKO": "202.44",
    "SATS": "83.57",
    "DDS": "585.96",
    "AN": "227.18",
    "SGHC": "13.15",
    "ATAT": "40.03",
    "SGI": "87.15",
    "PFGC": "106.25",
    "BMO": "126.95",
    "IX": "26.99",
    "PSLV": "14.3",
    "PFSI": "124.51",
    "NVS": "129.73",
    "HCA": "420.77",
    "ARGX": "768.0",
    "THC": "196.39",
    "MEDP": "497.59",
    "PODD": "352.82",
    "EHC": "126.8",
    "ASND": "205.91",
    "ENSG": "174.12",
    "HALO": "77.53",
    "VRNA": "106.31",
    "ABVX": "90.0",
    "URI": "975.23",
    "FERG": "238.34",
    "PNR": "112.59",
    "NVT": "95.71",
    "ACM": "127.66",
    "CNM": "66.98",
    "MLI": "98.96",
    "AWI": "199.13",
    "ROAD": "125.2",
    "BE": "67.29",
    "MIR": "22.9",
    "REZI": "38.07",
    "KRMN": "64.33",
    "JLL": "314.41",
    "AVGO": "369.57",
    "ANET": "153.04",
    "GLW": "77.04",
    "STX": "196.81",
    "FLEX": "58.05",
    "CYBR": "471.19",
    "GWRE": "261.88",
    "FN": "372.57",
    "UI": "612.86",
    "NXT": "70.12",
    "CLS": "253.03",
    "CRDO": "163.96",
    "TSEM": "67.65",
    "LITE": "164.88",
    "LIF": "103.11",
    "SNDK": "86.13",
    "SBS": "23.59",
    "VMC": "301.65",
    "GFI": "38.02",
    "NEU": "848.94",
    "HL": "11.21",
    "NTES": "152.8",
    "TTWO": "248.78",
    "LYV": "174.06",
    "APP": "582.0",
    "ORLY": "107.82",
    "AZO": "4354.54",
    "EXPE": "222.19",
    "IBP": "279.47",
    "DORM": "166.34",
    "ATGE": "138.6",
    "HSBC": "69.16",
    "NMR": "7.55",
    "HOOD": "118.52",
    "BAP": "266.59",
    "ACT": "39.23",
    "BSX": "108.14",
    "MDGL": "453.8",
    "INSM": "147.2",
    "ALLE": "177.18",
    "ESLT": "509.54",
    "FSV": "208.43",
    "TSM": "260.44",
    "NET": "224.64",
    "CIEN": "132.5",
    "ALAB": "232.9",
    "IDCC": "324.87",
    "ESE": "210.32",
    "NBIS": "95.72",
    "CASY": "553.99",
    "FTI": "40.89",
    "MS": "156.48",
    "GS": "784.73",
    "C": "99.44",
    "SAN": "10.08",
    "IREN": "33.96",
    "ALNY": "482.13",
    "MRUS": "69.8",
    "AHR": "43.16",
    "APH": "119.47",
    "RDDT": "260.54",
    "MOD": "151.5",
    "ENB": "49.1",
    "MFG": "6.71",
    "CG": "67.4",
    "HLI": "208.15",
    "EVR": "343.35",
    "ROIV": "14.41",
    "GE": "283.41",
    "FIX": "764.91",
    "ITT": "178.47",
    "MTZ": "190.12",
    "IESC": "381.19",
    "ORCL": "328.37",
    "TEL": "212.4",
    "HPE": "24.86",
    "PSTG": "82.46",
    "FFIV": "334.59",
    "TTMI": "49.43",
    "TLN": "402.65",
    "CRH": "114.47",
    "RGLD": "189.32",
    "VIK": "65.32",
    "GPI": "488.25",
    "LOPE": "209.66",
    "GHC": "1176.9",
    "JPM": "306.91",
    "BAC": "50.75",
    "UBS": "40.9",
    "BN": "68.86",
    "ING": "25.4",
    "TRV": "279.43",
    "BCS": "20.79",
    "CM": "79.55",
    "L": "98.05",
    "MTG": "28.92",
    "AMG": "236.11",
    "PJT": "186.9",
    "THG": "182.1",
    "BNT": "68.87",
    "ABCB": "74.63",
    "ABBV": "220.22",
    "LH": "279.72",
    "GD": "329.62",
    "PH": "769.67",
    "LHX": "280.63",
    "CMI": "411.03",
    "RBA": "118.71",
    "CHRW": "132.41",
    "PAC": "256.99",
    "STN": "112.26",
    "AYI": "339.44",
    "R": "189.57",
    "VMI": "386.7",
    "GATX": "171.38",
    "BCO": "117.52",
    "STRL": "316.16",
    "PRIM": "122.76",
    "CBRE": "165.9",
    "LRCX": "116.96",
    "KLAC": "964.02",
    "SONY": "29.21",
    "TDY": "566.11",
    "RMBS": "88.58",
    "NVMI": "293.1",
    "BDC": "133.49",
    "MNST": "64.69",
    "BK": "106.48",
    "DB": "37.16",
    "SOFI": "26.55",
    "KTOS": "69.2",
    "MU": "157.23",
    "IONQ": "55.61"
}