{
    "white_keywords": [
        "SNOW",
        "ELP",
        "LI",
        "FIVE",
        "TAP",
        "STVN",
        "JBHT",
        "GILD",
        "LULU",
        "GGB",
        "PATH",
        "DOX"
    ],
    "yellow_keywords": [
        "CNYJPY",
        "NASDAQ",
        "Gold",
        "Cocoa",
        "Silver",
        "IntermedTreary",
        "IndiaETF"
    ],
    "orange_keywords": [
        "HANGSENG",
        "Naturalgas",
        "Ether",
        "Shanghai",
        "USDCNY",
        "CZR",
        "DEO",
        "JNJ",
        "UPS",
        "CVS",
        "PCTY"
    ],
    "purple_keywords": [
        "Bitcoin",
        "CNYUSD",
        "US10Y",
        "USDJPY",
        "CrudeOil",
        "PAYC",
        "BF-B",
        "BMY"
    ],
    "black_keywords": [
        "Cotton",
        "Sugar",
        "U",
        "VFC",
        "WBA",
        "SOLV",
        "ZI",
        "ALAB"
    ],
    "blue_keywords": [
        "Copper",
        "S&P500",
        "USDINR"
    ],
    "red_keywords": [
        "VIX",
        "DXY",
        "USInterest",
        "CorePCEM"
    ],
    "green_keywords": [
        "EURCNY"
    ]
}